top_kat-0.1.1.dist-info/METADATA
top_kat-0.1.1.dist-info/WHEEL
top_kat/__init__.py
top_kat/top_kat.cp311-win32.pyd
top_kat-0.1.1.dist-info/RECORD
