Metadata-Version: 2.1
Name: top-kat
Version: 0.1.1
Classifier: Programming Language :: Rust
Classifier: Programming Language :: Python :: Implementation :: CPython
Classifier: Programming Language :: Python :: Implementation :: PyPy
Summary: A collection of streaming algorithms.
Keywords: streaming,algorithms
Author-email: cat pouch <isaac@bytewax.io>
Requires-Python: >=3.7
